Metadata-Version: 2.1
Name: owattr
Version: 0.10.0
Summary: owattr overwrites attributes.
Home-page: https://github.com/narusemotoki/owattr
Author: Motoki Naruse
Author-email: motoki@naru.se
License: MIT
Keywords: attrs,overwrite
Platform: UNKNOWN
Classifier: Development Status :: 4 - Beta
Classifier: Intended Audience :: Developers
Classifier: License :: OSI Approved :: MIT License
Classifier: Programming Language :: Python :: 3
Classifier: Programming Language :: Python :: 3.5
Classifier: Programming Language :: Python :: 3.6
Classifier: Programming Language :: Python :: 3 :: Only
Classifier: Topic :: Software Development :: Libraries
Provides-Extra: test
